traj_dist/__init__.py
traj_dist/benchmark.py
traj_dist/build_benchmark_data.py
traj_dist/distance.py
traj_dist/example.py
traj_dist/pydist/__init__.py
traj_dist/pydist/basic_euclidean.py
traj_dist/pydist/basic_spherical.py
traj_dist/pydist/discret_frechet.py
traj_dist/pydist/dtw.py
traj_dist/pydist/edr.py
traj_dist/pydist/erp.py
traj_dist/pydist/frechet.py
traj_dist/pydist/hausdorff.py
traj_dist/pydist/lcss.py
traj_dist/pydist/linecell.py
traj_dist/pydist/segment_distance.py
traj_dist/pydist/sowd.py
traj_dist/pydist/sspd.py
traj_dist2-0.0.3.dist-info/licenses/LICENSE.txt
traj_dist2-0.0.3.dist-info/METADATA
traj_dist2-0.0.3.dist-info/WHEEL
traj_dist2-0.0.3.dist-info/top_level.txt
traj_dist2-0.0.3.dist-info/RECORD
