Metadata-Version: 2.4
Name: traj_dist2
Version: 0.0.3
Summary: Distance to compare 2D-trajectories in Pure Python
Home-page: https://github.com/bguillouet/traj-dist
Author: Brendan Guillouet
Author-email: brendan.guillouet@gmail.com
License: MIT
Keywords: trajectory,distance,haversine
License-File: LICENSE.txt
Requires-Dist: numpy>=1.16.2
Requires-Dist: Shapely>=1.6.4
Requires-Dist: geohash2==1.1
Requires-Dist: pandas>=0.20.3
Requires-Dist: scipy>=0.19.1
Dynamic: author
Dynamic: author-email
Dynamic: home-page
Dynamic: keywords
Dynamic: license
Dynamic: license-file
Dynamic: requires-dist
Dynamic: summary
